controlnet/__init__.py
controlnet/config.py
controlnet/gradio_annotator.py
controlnet/gradio_canny2image.py
controlnet/gradio_depth2image.py
controlnet/gradio_fake_scribble2image.py
controlnet/gradio_hed2image.py
controlnet/gradio_hough2image.py
controlnet/gradio_normal2image.py
controlnet/gradio_pose2image.py
controlnet/gradio_pose2image_v2.py
controlnet/gradio_scribble2image.py
controlnet/gradio_scribble2image_interactive.py
controlnet/gradio_seg2image.py
controlnet/share.py
controlnet/tool_add_control.py
controlnet/tool_add_control_sd21.py
controlnet/tool_transfer_control.py
controlnet/tutorial_dataset.py
controlnet/tutorial_dataset_test.py
controlnet/tutorial_train.py
controlnet/tutorial_train_sd21.py
controlnet/annotator/__init__.py
controlnet/annotator/util.py
controlnet/annotator/canny/__init__.py
controlnet/annotator/hed/__init__.py
controlnet/annotator/midas/__init__.py
controlnet/annotator/midas/api.py
controlnet/annotator/midas/utils.py
controlnet/annotator/midas/midas/__init__.py
controlnet/annotator/midas/midas/base_model.py
controlnet/annotator/midas/midas/blocks.py
controlnet/annotator/midas/midas/dpt_depth.py
controlnet/annotator/midas/midas/midas_net.py
controlnet/annotator/midas/midas/midas_net_custom.py
controlnet/annotator/midas/midas/transforms.py
controlnet/annotator/midas/midas/vit.py
controlnet/annotator/mlsd/__init__.py
controlnet/annotator/mlsd/utils.py
controlnet/annotator/openpose/__init__.py
controlnet/annotator/openpose/body.py
controlnet/annotator/openpose/hand.py
controlnet/annotator/openpose/model.py
controlnet/annotator/openpose/util.py
controlnet/annotator/uniformer/__init__.py
controlnet/annotator/uniformer/mmcv/__init__.py
controlnet/annotator/uniformer/mmcv/version.py
controlnet/annotator/uniformer/mmcv/arraymisc/__init__.py
controlnet/annotator/uniformer/mmcv/arraymisc/quantization.py
controlnet/annotator/uniformer/mmcv/cnn/__init__.py
controlnet/annotator/uniformer/mmcv/cnn/alexnet.py
visor_controlnet-1.1.dist-info/METADATA
visor_controlnet-1.1.dist-info/WHEEL
visor_controlnet-1.1.dist-info/top_level.txt
visor_controlnet-1.1.dist-info/RECORD
